settipy.py
settipy_pure_python-1.0.1.dist-info/METADATA
settipy_pure_python-1.0.1.dist-info/WHEEL
settipy_pure_python-1.0.1.dist-info/top_level.txt
settipy_pure_python-1.0.1.dist-info/RECORD
