Metadata-Version: 2.1
Name: settipy-pure-python
Version: 1.0.1
Summary: settings should be simple, boring and forget-able. With settipy it will be just that. Without dependencies pure python
Home-page: https://github.com/Attumm/settipy_pure_python
Author: Melvin Bijman
Author-email: bijman.m.m@gmail.com
License: MIT
Classifier: Development Status :: 5 - Production/Stable
Classifier: Intended Audience :: Developers
Classifier: License :: OSI Approved :: MIT License
Classifier: Programming Language :: Python :: 3
Classifier: Programming Language :: Python :: 3.5
Classifier: Programming Language :: Python :: 3.6
Classifier: Programming Language :: Python :: 3.7
Classifier: Programming Language :: Python :: 3.8
Classifier: Programming Language :: Python :: 3.9
